finpricing/__init__.py
finpricing/finpricing.py
finpricing/instrument/__init__.py
finpricing/instrument/cds.py
finpricing/instrument/fixed_bond.py
finpricing/instrument/fixed_coupon_leg.py
finpricing/instrument/legacy/cds.py
finpricing/instrument/legacy/deposit.py
finpricing/instrument/legacy/swap_fixed_leg.py
finpricing/instrument/legacy/swap_float_leg.py
finpricing/instrument/legacy/vanilla_swap.py
finpricing/instrument/principal_leg.py
finpricing/market/__init__.py
finpricing/market/cds_curve.py
finpricing/market/discount_curve_zero.py
finpricing/market/legacy/curve.py
finpricing/market/legacy/discount_curve.py
finpricing/market/legacy/dummy_curve.py
finpricing/market/legacy/survival_curve.py
finpricing/market/lgd_curve.py
finpricing/market/recovery_curve.py
finpricing/market/survival_curve_ns.py
finpricing/market/survival_curve_step.py
finpricing/model/__init__.py
finpricing/model/bond_basis_solver.py
finpricing/model/bond_curve_solver.py
finpricing/model/cds_analytics.py
finpricing/model/cds_pricer.py
finpricing/model/fixed_bond_pricer.py
finpricing/model/utils/__init__.py
finpricing/model/utils/bond_pricing_utils.py
finpricing/utils/__init__.py
finpricing/utils/bus_day_adj.py
finpricing/utils/calendar.py
finpricing/utils/cds_style.py
finpricing/utils/date.py
finpricing/utils/date_generator.py
finpricing/utils/day_count.py
finpricing/utils/error.py
finpricing/utils/frequency.py
finpricing/utils/holiday.py
finpricing/utils/instaplot.py
finpricing/utils/interpolator.py
finpricing/utils/legacy/bootstrap_tools.py
finpricing/utils/legacy/reconcile.py
finpricing/utils/literal.py
finpricing/utils/pandas_holiday.py
finpricing/utils/payment_schedule.py
finpricing/utils/tools.py
finpricing-0.1.0.dist-info/LICENSE
finpricing-0.1.0.dist-info/METADATA
finpricing-0.1.0.dist-info/WHEEL
finpricing-0.1.0.dist-info/RECORD
