Metadata-Version: 2.1
Name: finpricing
Version: 0.1.0
Summary: A pricing library for financial instruments
License: MIT
Author: Yiming Zhang
Requires-Python: >=3.9,<3.13
Classifier: License :: OSI Approved :: MIT License
Classifier: Programming Language :: Python :: 3
Classifier: Programming Language :: Python :: 3.9
Classifier: Programming Language :: Python :: 3.10
Classifier: Programming Language :: Python :: 3.11
Requires-Dist: numpy (>=1.26.1,<2.0.0)
Requires-Dist: prettytable (>=3.9.0,<4.0.0)
Requires-Dist: python-dateutil (>=2.8.2,<3.0.0)
Requires-Dist: scipy (>=1.11.3,<2.0.0)
